diki_scraper/__init__.py
diki_scraper/diki.py
diki_scraper-1.3.dist-info/LICENSE
diki_scraper-1.3.dist-info/METADATA
diki_scraper-1.3.dist-info/WHEEL
diki_scraper-1.3.dist-info/top_level.txt
diki_scraper-1.3.dist-info/RECORD
