Metadata-Version: 2.1
Name: diki-scraper
Version: 1.3
Summary: A library for generating diki.pl ENG-PL translations
Home-page: https://github.com/mepavv/diki_scraper
Author: Michał Pawłowski
Author-email: <michal.paw000@gmail.com>
License: MIT
Keywords: scraper,api,translation,polish,english
Classifier: Development Status :: 5 - Production/Stable
Classifier: Intended Audience :: Developers
Classifier: Programming Language :: Python :: 3
Classifier: Operating System :: Unix
Classifier: Operating System :: MacOS :: MacOS X
Classifier: Operating System :: Microsoft :: Windows
License-File: LICENSE
Requires-Dist: requests
Requires-Dist: beautifulsoup4
